comb_utils/__init__.py
comb_utils/lib/__init__.py
comb_utils/lib/api_callers.py
comb_utils/lib/constants.py
comb_utils/lib/docs.py
comb_utils/lib/errors.py
comb_utils-0.5.3.dist-info/licenses/LICENSE
comb_utils-0.5.3.dist-info/METADATA
comb_utils-0.5.3.dist-info/WHEEL
comb_utils-0.5.3.dist-info/top_level.txt
comb_utils-0.5.3.dist-info/RECORD
