Metadata-Version: 2.4
Name: comb_utils
Version: 0.5.3
Summary: Handy utils for Python projects.
Author: Kaleb Coberly
Maintainer-email: kaleb.coberly@gmail.com
Requires-Python: >=3.12
License-File: LICENSE
Requires-Dist: requests<3.0.0,>=2.32.3
Requires-Dist: typeguard<5.0.0,>=4.4.4
Provides-Extra: dev
Requires-Dist: comb_utils[build]; extra == "dev"
Requires-Dist: comb_utils[doc]; extra == "dev"
Requires-Dist: comb_utils[qc]; extra == "dev"
Requires-Dist: comb_utils[test]; extra == "dev"
Provides-Extra: build
Requires-Dist: build; extra == "build"
Requires-Dist: twine; extra == "build"
Requires-Dist: wheel; extra == "build"
Provides-Extra: doc
Requires-Dist: furo; extra == "doc"
Requires-Dist: sphinx; extra == "doc"
Requires-Dist: sphinx-autodoc-typehints; extra == "doc"
Provides-Extra: qc
Requires-Dist: bandit; extra == "qc"
Requires-Dist: black; extra == "qc"
Requires-Dist: flake8; extra == "qc"
Requires-Dist: flake8-annotations; extra == "qc"
Requires-Dist: flake8-bandit; extra == "qc"
Requires-Dist: flake8-black>=0.4.0; extra == "qc"
Requires-Dist: flake8-bugbear; extra == "qc"
Requires-Dist: flake8-docstrings; extra == "qc"
Requires-Dist: flake8-isort; extra == "qc"
Requires-Dist: isort; extra == "qc"
Requires-Dist: jake; extra == "qc"
Requires-Dist: pytype; python_version < "3.13" and extra == "qc"
Requires-Dist: comb_utils[test]; extra == "qc"
Requires-Dist: safety; extra == "qc"
Provides-Extra: test
Requires-Dist: coverage[toml]; extra == "test"
Requires-Dist: pytest; extra == "test"
Requires-Dist: pytest-cov; extra == "test"
Dynamic: license-file
